Metadata-Version: 2.1
Name: check_if_is_production
Version: 0.0.1
Summary: Check if an Odoo conneciton is running in production or not
Home-page: https://github.com/mateo-de-leonn/check_production_running
Author: Mateo De León
Author-email: mdeleon@proyectasoft.com
License: GPLv3
Classifier: Programming Language :: Python :: 3
Classifier: License :: OSI Approved :: GNU General Public License v3 (GPLv3)
Classifier: Operating System :: OS Independent
Requires-Python: >=3.9
License-File: LICENSE.txt
